django_global_places/__init__.py
django_global_places/__version__.py
django_global_places/abstract_models.py
django_global_places/admin.py
django_global_places/app_settings.py
django_global_places/apps.py
django_global_places/models.py
django_global_places/urls.py
django_global_places/utils.py
django_global_places/viewsets_utils.py
django_global_places/management/__init__.py
django_global_places/management/commands/__init__.py
django_global_places/management/commands/populate_global_places.py
django_global_places/migrations/0001_initial.py
django_global_places/migrations/0002_alter_state_state_code.py
django_global_places/migrations/__init__.py
django_global_places/serializers/__init__.py
django_global_places/serializers/cities.py
django_global_places/serializers/countries.py
django_global_places/serializers/states.py
django_global_places/views/__init__.py
django_global_places/views/cities.py
django_global_places/views/countries.py
django_global_places/views/states.py
django_global_places-0.10.1.dist-info/AUTHORS
django_global_places-0.10.1.dist-info/LICENSE
django_global_places-0.10.1.dist-info/METADATA
django_global_places-0.10.1.dist-info/WHEEL
django_global_places-0.10.1.dist-info/top_level.txt
django_global_places-0.10.1.dist-info/RECORD
