Metadata-Version: 2.2
Name: django_global_places
Version: 0.10.1
Summary: Django Global Places is a simple Django app to provide a model for global places.
Home-page: https://github.com/lucacitta/Django-GlobalPlaces
Author: lucacitta
Author-email: lucacitta.dev@gmail.com
License: MIT
Keywords: django global places
Classifier: Framework :: Django
Classifier: Intended Audience :: Developers
Classifier: Intended Audience :: System Administrators
Classifier: Operating System :: OS Independent
Classifier: Topic :: Software Development
Requires-Python: >=3.8
License-File: LICENSE
License-File: AUTHORS
Requires-Dist: Django>=3.8.0
Requires-Dist: pandas>=2.2.0
Requires-Dist: requests>=2.30
Dynamic: author
Dynamic: author-email
Dynamic: classifier
Dynamic: description
Dynamic: description-content-type
Dynamic: home-page
Dynamic: keywords
Dynamic: license
Dynamic: requires-dist
Dynamic: requires-python
Dynamic: summary
